agent_protocol/__init__.py
agent_protocol/agent.py
agent_protocol/cli.py
agent_protocol/db.py
agent_protocol/middlewares.py
agent_protocol/models.py
agent_protocol/server.py
agent_protocol/utils/__init__.py
agent_protocol/utils/compliance/__init__.py
agent_protocol/utils/compliance/conftest.py
agent_protocol/utils/compliance/main.py
agent_protocol-1.0.2.dist-info/METADATA
agent_protocol-1.0.2.dist-info/WHEEL
agent_protocol-1.0.2.dist-info/entry_points.txt
agent_protocol-1.0.2.dist-info/RECORD
