Metadata-Version: 2.1
Name: agent-protocol
Version: 1.0.2
Summary: API for interacting with Agents that use the Agent Protocol
Home-page: https://agentprotocol.ai/
License: MIT
Author: AI Engineers Foundation
Author-email: aiengineersfoundation@gmail.com
Requires-Python: >=3.10,<4.0.0
Classifier: License :: OSI Approved :: MIT License
Classifier: Programming Language :: Python :: 3
Classifier: Programming Language :: Python :: 3.10
Classifier: Programming Language :: Python :: 3.11
Requires-Dist: aiofiles (>=23.1.0,<24.0.0)
Requires-Dist: click (>=8.1.6,<9.0.0)
Requires-Dist: fastapi (>=0.100.0,<0.101.0)
Requires-Dist: hypercorn (>=0.14.4,<0.15.0)
Requires-Dist: pydantic (>=1.10.5,<2.0.0)
Requires-Dist: pytest (>=7.0.0,<8.0.0)
Requires-Dist: python-multipart (>=0.0.6,<0.0.7)
Requires-Dist: requests (>=2.31.0,<3.0.0)
Project-URL: Bug Tracker, https://github.com/AI-Engineers-Foundation/agent-protocol/issues
Project-URL: Repository, https://github.com/AI-Engineers-Foundation/agent-protocol/tree/main/packages/sdk/python
